README.rst
setup.py
intertechno/VERSION
intertechno/__init__.py
intertechno/timers.py
intertechno.egg-info/PKG-INFO
intertechno.egg-info/SOURCES.txt
intertechno.egg-info/dependency_links.txt
intertechno.egg-info/top_level.txt