Metadata-Version: 1.1
Name: intertechno
Version: 0.2
Summary: Library for communicating with intertechno devices.
Home-page: https://github.com/smart-home-technology/intertechno-python
Author: Smart-Home Technology GmbH
Author-email: code@smart-home-technology.ch
License: MIT
Keywords: intertechno interface control home automation device
Platform: any
Classifier: Development Status :: 4 - Beta
Classifier: Intended Audience :: Developers
Classifier: Topic :: Home Automation
Classifier: License :: OSI Approved :: MIT License
Classifier: Programming Language :: Python :: 3
Classifier: Programming Language :: Python :: 2
Classifier: Operating System :: OS Independent
